smart_floorplan_predictor/__init__.py
smart_floorplan_predictor/predictor.py
smart_floorplan_predictor-1.0.0.dist-info/METADATA
smart_floorplan_predictor-1.0.0.dist-info/WHEEL
smart_floorplan_predictor-1.0.0.dist-info/top_level.txt
smart_floorplan_predictor-1.0.0.dist-info/RECORD
